bpiek/__init__.py
bpiek/api.py
bpiek/models/category.py
bpiek/models/product.py
bpiek/models/response.py
bpiek/utils.py
bpiek-1.1.8.dist-info/METADATA
bpiek-1.1.8.dist-info/WHEEL
bpiek-1.1.8.dist-info/RECORD
